CHANGES.txt
MANIFEST.in
README.txt
development.ini
production.ini
setup.cfg
setup.py
prism_rest/__init__.py
prism_rest/encoders.py
prism_rest/errors.py
prism_rest/renderer.py
prism_rest/viewmodels.py
prism_rest/views.py
prism_rest.egg-info/PKG-INFO
prism_rest.egg-info/SOURCES.txt
prism_rest.egg-info/dependency_links.txt
prism_rest.egg-info/entry_points.txt
prism_rest.egg-info/not-zip-safe
prism_rest.egg-info/requires.txt
prism_rest.egg-info/top_level.txt