Metadata-Version: 1.1
Name: prism-rest
Version: 0.0
Summary: prism_rest
Home-page: https://github.com/elliotpeele/prism_rest
Author: Elliot Peele
Author-email: elliot@bentlogic.net
License: UNKNOWN
Keywords: web wsgi bfg pylons pyramid rest
Platform: UNKNOWN
Classifier: Programming Language :: Python
Classifier: Framework :: Pyramid
Classifier: Topic :: Internet :: WWW/HTTP
Classifier: Topic :: Internet :: WWW/HTTP :: WSGI :: Application
